enigmacalc/__init__.py
enigmacalc-0.1.dist-info/LICENSE.txt
enigmacalc-0.1.dist-info/METADATA
enigmacalc-0.1.dist-info/WHEEL
enigmacalc-0.1.dist-info/top_level.txt
enigmacalc-0.1.dist-info/RECORD
