Metadata-Version: 2.1
Name: enigmacalc
Version: 0.1
Summary: basic calc
Home-page: UNKNOWN
Author: kiran
Author-email: kiran12.s2001@gmail.com
License: UNKNOWN
Platform: UNKNOWN
Classifier: Programming Language :: Python :: 3
Classifier: License :: OSI Approved :: MIT License
Classifier: Operating System :: OS Independent
License-File: LICENSE.txt
